{
  "pages": [
    {
      "id": 1,
      "name": "Page d'accueil",
      "route": "/",
      "components": []
    },
    {
      "id": 2,
      "name": "La nouvelle page",
      "route": "/page2",
      "components": []
    },
    {
      "name": "Test page",
      "route": "/toto",
      "components": [
        {
          "type": "TitleBanner",
          "content": "Bonjour, la bannière titre est ici",
          "imageUrl": "Osef non ?"
        },
        {
          "type": "TextArea",
          "content": "La zone de texte est ici !"
        }
      ],
      "id": 3
    }
  ]
}